chzzk/__init__.py
chzzk/chzzk.py
chzzk/client.py
chzzk/errors.py
chzzk/utils.py
chzzk/models/__init__.py
chzzk/models/raw.py
python_chzzk-0.0.2.dist-info/LICENSE
python_chzzk-0.0.2.dist-info/METADATA
python_chzzk-0.0.2.dist-info/WHEEL
python_chzzk-0.0.2.dist-info/top_level.txt
python_chzzk-0.0.2.dist-info/RECORD
