Metadata-Version: 2.1
Name: python-chzzk
Version: 0.0.2
Summary: An unofficial Python library for CHZZK
Home-page: https://github.com/jonghwanhyeon/python-chzzk
Author: Jonghwan Hyeon
Author-email: jonghwanhyeon93@gmail.com
License: MIT
Keywords: chzzk
Classifier: Development Status :: 4 - Beta
Classifier: License :: OSI Approved :: MIT License
Classifier: Programming Language :: Python :: 3
Classifier: Programming Language :: Python :: 3 :: Only
Requires-Python: >=3.8
License-File: LICENSE
Requires-Dist: httpx
Requires-Dist: pydantic
Requires-Dist: typing-extensions
